<?xml version="1.0" encoding="UTF-8"?>
<OpenSearchDescription xmlns="http://a9.com/-/spec/opensearch/1.1/">
    <ShortName>Yahoo奇摩!</ShortName>
    <Description>Yahoo奇摩!</Description>
    <InputEncoding>UTF-8</InputEncoding>
    <LongName>Yahoo奇摩!</LongName>
    <Language>*</Language>
    <Image height="16" width="16">https://s.yimg.com/rz/l/favicon.ico</Image>
    <Url type="text/html" method="GET" template="https://tw.search.yahoo.com/search">
        <Param name="p" value="{searchTerms}"/>
        <Param name="fr" value="opensearch"/>
    </Url>
    <Url type="application/x-suggestions+json" method="GET" template="https://tw.search.yahoo.com/sugg/os">
        <Param name="command" value="{searchTerms}"/>
        <Param name="output" value="fxjson"/>
        <Param name="fr" value="opensearch"/>
    </Url>
    <Url type="application/opensearchdescription+xml" template="https://tw.search.yahoo.com/opensearch.xml"/>
</OpenSearchDescription>
